{
    "utc_offset": -300, 
    "name": "MulaNoah Natural Organics", 
    "reference": "ChIJsVb0wZ0xK4gR76VKhsZyHoQ", 
    "geometry": {
        "location": {
            "lat": 43.7264948, 
            "lng": -79.48619479999999
        }, 
        "viewport": {
            "northeast": {
                "lat": 43.72750068029151, 
                "lng": -79.4846945697085
            }, 
            "southwest": {
                "lat": 43.72480271970851, 
                "lng": -79.4873925302915
            }
        }
    }, 
    "adr_address": "<span class=\"street-address\">1154 Wilson Ave #608</span>, <span class=\"locality\">North York</span>, <span class=\"region\">ON</span> <span class=\"postal-code\">M3M 1J6</span>, <span class=\"country-name\">Canada</span>", 
    "place_id": "ChIJsVb0wZ0xK4gR76VKhsZyHoQ", 
    "international_phone_number": "+1 416-638-4894", 
    "plus_code": {
        "global_code": "87M2PGG7+HG", 
        "compound_code": "PGG7+HG Toronto, Ontario, Canada"
    }, 
    "formatted_phone_number": "(416) 638-4894", 
    "scope": "GOOGLE", 
    "url": "https://maps.google.com/?cid=9520172859289937391", 
    "opening_hours": {
        "weekday_text": [
            "Monday: 8:00 AM \u2013 12:00 PM", 
            "Tuesday: 8:00 AM \u2013 12:00 PM", 
            "Wednesday: 8:00 AM \u2013 12:00 PM", 
            "Thursday: 8:00 AM \u2013 12:00 PM", 
            "Friday: 8:00 AM \u2013 12:00 PM", 
            "Saturday: 8:00 AM \u2013 12:00 PM", 
            "Sunday: 8:00 AM \u2013 12:00 PM"
        ], 
        "open_now": false, 
        "periods": [
            {
                "close": {
                    "day": 0, 
                    "time": "1200"
                }, 
                "open": {
                    "day": 0, 
                    "time": "0800"
                }
            }, 
            {
                "close": {
                    "day": 1, 
                    "time": "1200"
                }, 
                "open": {
                    "day": 1, 
                    "time": "0800"
                }
            }, 
            {
                "close": {
                    "day": 2, 
                    "time": "1200"
                }, 
                "open": {
                    "day": 2, 
                    "time": "0800"
                }
            }, 
            {
                "close": {
                    "day": 3, 
                    "time": "1200"
                }, 
                "open": {
                    "day": 3, 
                    "time": "0800"
                }
            }, 
            {
                "close": {
                    "day": 4, 
                    "time": "1200"
                }, 
                "open": {
                    "day": 4, 
                    "time": "0800"
                }
            }, 
            {
                "close": {
                    "day": 5, 
                    "time": "1200"
                }, 
                "open": {
                    "day": 5, 
                    "time": "0800"
                }
            }, 
            {
                "close": {
                    "day": 6, 
                    "time": "1200"
                }, 
                "open": {
                    "day": 6, 
                    "time": "0800"
                }
            }
        ]
    }, 
    "vicinity": "1154 Wilson Avenue #608, North York", 
    "address_components": [
        {
            "long_name": "608", 
            "types": [
                "subpremise"
            ], 
            "short_name": "608"
        }, 
        {
            "long_name": "1154", 
            "types": [
                "street_number"
            ], 
            "short_name": "1154"
        }, 
        {
            "long_name": "Wilson Avenue", 
            "types": [
                "route"
            ], 
            "short_name": "Wilson Ave"
        }, 
        {
            "long_name": "North York", 
            "types": [
                "sublocality_level_1", 
                "sublocality", 
                "political"
            ], 
            "short_name": "North York"
        }, 
        {
            "long_name": "Toronto", 
            "types": [
                "locality", 
                "political"
            ], 
            "short_name": "Toronto"
        }, 
        {
            "long_name": "Toronto Division", 
            "types": [
                "administrative_area_level_2", 
                "political"
            ], 
            "short_name": "Toronto Division"
        }, 
        {
            "long_name": "Ontario", 
            "types": [
                "administrative_area_level_1", 
                "political"
            ], 
            "short_name": "ON"
        }, 
        {
            "long_name": "Canada", 
            "types": [
                "country", 
                "political"
            ], 
            "short_name": "CA"
        }, 
        {
            "long_name": "M3M 1J6", 
            "types": [
                "postal_code"
            ], 
            "short_name": "M3M 1J6"
        }
    ], 
    "formatted_address": "1154 Wilson Ave #608, North York, ON M3M 1J6, Canada", 
    "id": "1c3f44a8a399a8cacc911b233ebc91b5a96e40c0", 
    "types": [
        "store", 
        "point_of_interest", 
        "establishment"
    ], 
    "icon": "https://maps.gstatic.com/mapfiles/place_api/icons/shopping-71.png"
}