{
    "address_components": [
        {
            "long_name": "2181",
            "short_name": "2181",
            "types": [
                "street_number"
            ]
        },
        {
            "long_name": "Queen Street East",
            "short_name": "Queen St E",
            "types": [
                "route"
            ]
        },
        {
            "long_name": "Old Toronto",
            "short_name": "Old Toronto",
            "types": [
                "sublocality_level_1",
                "sublocality",
                "political"
            ]
        },
        {
            "long_name": "Toronto",
            "short_name": "Toronto",
            "types": [
                "locality",
                "political"
            ]
        },
        {
            "long_name": "Toronto Division",
            "short_name": "Toronto Division",
            "types": [
                "administrative_area_level_2",
                "political"
            ]
        },
        {
            "long_name": "Ontario",
            "short_name": "ON",
            "types": [
                "administrative_area_level_1",
                "political"
            ]
        },
        {
            "long_name": "Canada",
            "short_name": "CA",
            "types": [
                "country",
                "political"
            ]
        },
        {
            "long_name": "M4E 1E5",
            "short_name": "M4E 1E5",
            "types": [
                "postal_code"
            ]
        }
    ],
    "adr_address": "<span class=\"street-address\">2181 Queen St E</span>, <span class=\"locality\">Toronto</span>, <span class=\"region\">ON</span> <span class=\"postal-code\">M4E 1E5</span>, <span class=\"country-name\">Canada</span>",
    "formatted_address": "2181 Queen St E, Toronto, ON M4E 1E5, Canada",
    "formatted_phone_number": "(416) 686-6621",
    "geometry": {
        "location": {
            "lat": 43.6705075,
            "lng": -79.29745
        },
        "viewport": {
            "northeast": {
                "lat": 43.6718947302915,
                "lng": -79.29611676970849
            },
            "southwest": {
                "lat": 43.6691967697085,
                "lng": -79.29881473029151
            }
        }
    },
    "icon": "https://maps.gstatic.com/mapfiles/place_api/icons/school-71.png",
    "id": "5d12dba0870af5a4d7a6d1a7bc894944453793c0",
    "international_phone_number": "+1 416-686-6621",
    "name": "Avalon Children's Montessori School",
    "opening_hours": {
        "open_now": false,
        "periods": [
            {
                "close": {
                    "day": 1,
                    "time": "1700"
                },
                "open": {
                    "day": 1,
                    "time": "0800"
                }
            },
            {
                "close": {
                    "day": 2,
                    "time": "1700"
                },
                "open": {
                    "day": 2,
                    "time": "0800"
                }
            },
            {
                "close": {
                    "day": 3,
                    "time": "1700"
                },
                "open": {
                    "day": 3,
                    "time": "0800"
                }
            },
            {
                "close": {
                    "day": 4,
                    "time": "1700"
                },
                "open": {
                    "day": 4,
                    "time": "0800"
                }
            },
            {
                "close": {
                    "day": 5,
                    "time": "1700"
                },
                "open": {
                    "day": 5,
                    "time": "0800"
                }
            }
        ],
        "weekday_text": [
            "Monday: 8:00 AM \u2013 5:00 PM",
            "Tuesday: 8:00 AM \u2013 5:00 PM",
            "Wednesday: 8:00 AM \u2013 5:00 PM",
            "Thursday: 8:00 AM \u2013 5:00 PM",
            "Friday: 8:00 AM \u2013 5:00 PM",
            "Saturday: Closed",
            "Sunday: Closed"
        ]
    },
    "photos": [
        {
            "height": 720,
            "html_attributions": [
                "<a href=\"https://maps.google.com/maps/contrib/111936902404400727794/photos\">Avalon Children&#39;s Montessori School</a>"
            ],
            "photo_reference": "CmRaAAAAblQKttfDiqjmHEIdGu_PR7j0xsro4CacJGTTwwbdZ2-k5gyg1dlB8TRNhtmyGmc7gMpL2rt7pDQ-sMbXl-XLYix7wJLyR1ASzFrFWrDDeGbqiCdJ9l2af6iOYlSqHx08EhDjFOoJhrzlbrhAAXv4aiivGhR5a_k33Wp8A-l53zPAbKvte9bVqg",
            "width": 960
        },
        {
            "height": 960,
            "html_attributions": [
                "<a href=\"https://maps.google.com/maps/contrib/111936902404400727794/photos\">Avalon Children&#39;s Montessori School</a>"
            ],
            "photo_reference": "CmRaAAAAwh0Ar8tG4JdkFRLpEHDmzxl3Z3MlQSwWesXyvKXHYPwPR-OrZrilY1kfQUVr_oMv4MSPMfLOGzw1lSou2r9inGOFAqQEjoYN8jNHjZHv0wBTthzQe8dip80eiNxsQlBrEhChzWhdhcrPLhoCYedZPOTHGhTkm7K5dJd4CNYC9r6B_-UJj8DQXg",
            "width": 1280
        },
        {
            "height": 480,
            "html_attributions": [
                "<a href=\"https://maps.google.com/maps/contrib/111936902404400727794/photos\">Avalon Children&#39;s Montessori School</a>"
            ],
            "photo_reference": "CmRaAAAAIfsIjkWC8ah07K-f--bC0Vcqh9j6-ZA3ZsDtw2a0g0ZibY-aH28G5IGsVHl7OOk9anOgNQiq0Ffn_sJKJiWlZrKSvu0H1DHqwqpXE30-BjSYomHEiaGN217t4V4RZHI1EhAou-AyRlvLHgi8PWqs9ZA7GhTkUMTPwgN2sHkCzolT4JTYzkYVng",
            "width": 640
        },
        {
            "height": 417,
            "html_attributions": [
                "<a href=\"https://maps.google.com/maps/contrib/111936902404400727794/photos\">Avalon Children&#39;s Montessori School</a>"
            ],
            "photo_reference": "CmRaAAAAsqfw841AwIC1fRZZCL29DIS11U4fQLbnTOKzstgvYQ7uKVaEuGDNxHjylVsIGdsYWoUS0SePbVNbAewIx7yERcA4xicSLRgvNF1pgMIklaKlUMX3lV2xNlGk2cMp6JmiEhD5FeXMRK9NzB8JXYx_dsYHGhTcqVxRVQs7Gg_S3tnLqL6wjfKnEA",
            "width": 640
        },
        {
            "height": 1247,
            "html_attributions": [
                "<a href=\"https://maps.google.com/maps/contrib/111936902404400727794/photos\">Avalon Children&#39;s Montessori School</a>"
            ],
            "photo_reference": "CmRaAAAAEzJLwrFikLAbKTTPm_UvOf1lPVZGUY4LecbcrZLTY54jzpkowx8YSSSS4rcoeiTbBQ802alrtlKH4tfS2Rz4A3xIFAR14hReOLFREnpH2k8esoh1FbqkfBeeU-DRqGo7EhDE04qE5Jk8BwUrimkTCZv7GhThwZol4OmPYtl0zWx9UrAkC3qE8w",
            "width": 1004
        },
        {
            "height": 720,
            "html_attributions": [
                "<a href=\"https://maps.google.com/maps/contrib/111936902404400727794/photos\">Avalon Children&#39;s Montessori School</a>"
            ],
            "photo_reference": "CmRaAAAANjEHd_hHVmkRFdW3_8aRgw8SuZCSpj4Wdg_LX5bzos5EaqRzcDTt4M2FlEFg76jN9SLKQCH4F1CXN3Khmayh8pKRnFD-xpGUxMt7RfjJas9AB49uJT1mAFyxYr0A94vuEhAAvgGOA0NyNkO2FyeIqR72GhTBvGWEgh97ugykVWtC8aoBydYzCw",
            "width": 960
        },
        {
            "height": 960,
            "html_attributions": [
                "<a href=\"https://maps.google.com/maps/contrib/111936902404400727794/photos\">Avalon Children&#39;s Montessori School</a>"
            ],
            "photo_reference": "CmRaAAAAonuUqEqnXX6_1rdDbH3ESNPMGskL9UfH-1Kkp9XLBZ0iVHs__u1OnnZIqhzwtr3ULiVahQel-DwXQdS04IRIfeYb0mlYY7rdOiNXw9twnGEusXgHAoitdnxUcg4xD8GkEhBHRkU1gVSAWscnEnwrWp36GhTS8o0bG_hNXftX3V3EjVvx0DrJNA",
            "width": 716
        },
        {
            "height": 1367,
            "html_attributions": [
                "<a href=\"https://maps.google.com/maps/contrib/111936902404400727794/photos\">Avalon Children&#39;s Montessori School</a>"
            ],
            "photo_reference": "CmRaAAAAtX4y8kXWaFAsH1SlfXeMAdNH2ptBigF3p_dGbP42lZSCu7aBRaSJ4d_fQv45Vy0L80oaTEgFddPPwjuaO6A0Rwd3QJHYu15HYdE0RLdlbuAqz9el0tSh5SQyNvSslnmeEhBtG3KphjmjYdHeW6_eCOmbGhSN5vMGZFJd6Y8niIbbJwaVj6AkEQ",
            "width": 2048
        },
        {
            "height": 960,
            "html_attributions": [
                "<a href=\"https://maps.google.com/maps/contrib/111936902404400727794/photos\">Avalon Children&#39;s Montessori School</a>"
            ],
            "photo_reference": "CmRaAAAAjhuDBt_p25YrSZRruZCAzlO-5ThRFG954Ufho7MjSxcNQleElQuHFK_166FJnZrsP0swuTI9ds2XhNVHptDjr8Ik1fy_1gKuiXCwK4nk5CwvvLyXiUX_fjPQac6yDQL-EhAtDeJoXWbQih4d2oYVXKOqGhQ50gSfufsyKBFvgHDY1zHCmlCH-A",
            "width": 720
        },
        {
            "height": 960,
            "html_attributions": [
                "<a href=\"https://maps.google.com/maps/contrib/111936902404400727794/photos\">Avalon Children&#39;s Montessori School</a>"
            ],
            "photo_reference": "CmRaAAAA6yhZF4BF1Y7vH_2IyYbNVPTxi3aYDMg_1Sxnj0pHAJ3eYD3qbpuF5qlZLKT2iqPjXRyQ2kaYOTPfXhPwmnxxCcf7v5FGnCy7YsMJZo9Fpjdl7XpgbVhalHZrtAw9kuyVEhDbQLI4V3pht9afLOFzPaibGhTZtUKIa13HsGJgWw2S79_zwYoaKg",
            "width": 740
        }
    ],
    "place_id": "ChIJ-amiLQfM1IkRw-zl9VVj_yA",
    "rating": 4.3,
    "reference": "CmRRAAAAi9DNd6EZjVOaslHCmPyaOZoLrN0ghQMbKCTinJapOZipVBo9IjLbgzyMHwICyvvD5aHNhJ8YjfzUhkCCD6NJrV4bdldFHYddftgEwPhe0xq_SJ8MDYFVOOjZCUCYtfpnEhAQ_u3pFWtPeK_Q7KWgsGulGhRdlfrJcQpNbi44J2i14lIWUM4Mgg",
    "reviews": [
        {
            "author_name": "Tanya Solonyka",
            "author_url": "https://www.google.com/maps/contrib/106173385167640247082/reviews",
            "language": "en",
            "profile_photo_url": "https://lh3.googleusercontent.com/-1lCV38OBwSg/AAAAAAAAAAI/AAAAAAAAk-8/oxbdxK61kz4/s128-c0x00000000-cc-rp-mo/photo.jpg",
            "rating": 5,
            "relative_time_description": "a month ago",
            "text": "Thank you so much to the teachers at Avalon for creating an environment where my once incredibly shy little boy has been given the tools to thrive. It's moments like these that make me feel so proud to be part of the Avalon family. All of your hard work DOES pay off. I see it every day as his confidence grows. It's so wonderful that the school embraces the arts and gives the students a chance to flex their wings and shine. Everyone did a wonderful job! Thank you thank you.",
            "time": 1524509641
        },
        {
            "author_name": "King - Butt",
            "author_url": "https://www.google.com/maps/contrib/112230102036098479628/reviews",
            "language": "en",
            "profile_photo_url": "https://lh6.googleusercontent.com/-bJ1SjEIxNnE/AAAAAAAAAAI/AAAAAAAAAAA/AB6qoq3FBJ9bZ4OqZSmY5-3spvt8BKZ3IA/s128-c0x00000000-cc-rp-mo/photo.jpg",
            "rating": 5,
            "relative_time_description": "4 weeks ago",
            "text": "Avalon Children's Montessori School, is an exceptional elementary school right in the heart of the beach.  The teachers have a firm understanding of Montessori's guiding principals, the level of support the owner's provided my children with was remarkable.  I have happy, self directed, life long learners thanks to Avalon Children's Montessori school .  The staff, the owners, the parents and the children are wonderful, Avalon is truly a caring community.",
            "time": 1527099734
        },
        {
            "author_name": "Brady Knox",
            "author_url": "https://www.google.com/maps/contrib/106828364962728738656/reviews",
            "profile_photo_url": "https://lh5.googleusercontent.com/-QmqzC5B2sis/AAAAAAAAAAI/AAAAAAAAAAg/shbgG_biXBs/s128-c0x00000000-cc-rp-mo/photo.jpg",
            "rating": 3,
            "relative_time_description": "4 months ago",
            "text": "",
            "time": 1517501833
        }
    ],
    "scope": "GOOGLE",
    "types": [
        "school",
        "point_of_interest",
        "establishment"
    ],
    "url": "https://maps.google.com/?cid=2377728349123767491",
    "utc_offset": -240,
    "vicinity": "2181 Queen Street East, Toronto",
    "website": "http://www.avalonmontessori.ca/"
}