{
    "address_components": [
        {
            "long_name": "220",
            "short_name": "220",
            "types": [
                "street_number"
            ]
        },
        {
            "long_name": "Langley Avenue",
            "short_name": "Langley Ave",
            "types": [
                "route"
            ]
        },
        {
            "long_name": "Old Toronto",
            "short_name": "Old Toronto",
            "types": [
                "sublocality_level_1",
                "sublocality",
                "political"
            ]
        },
        {
            "long_name": "Toronto",
            "short_name": "Toronto",
            "types": [
                "locality",
                "political"
            ]
        },
        {
            "long_name": "Toronto Division",
            "short_name": "Toronto Division",
            "types": [
                "administrative_area_level_2",
                "political"
            ]
        },
        {
            "long_name": "Ontario",
            "short_name": "ON",
            "types": [
                "administrative_area_level_1",
                "political"
            ]
        },
        {
            "long_name": "Canada",
            "short_name": "CA",
            "types": [
                "country",
                "political"
            ]
        },
        {
            "long_name": "M4K 3H9",
            "short_name": "M4K 3H9",
            "types": [
                "postal_code"
            ]
        }
    ],
    "adr_address": "<span class=\"street-address\">220 Langley Ave</span>, <span class=\"locality\">Toronto</span>, <span class=\"region\">ON</span> <span class=\"postal-code\">M4K 3H9</span>, <span class=\"country-name\">Canada</span>",
    "formatted_address": "220 Langley Ave, Toronto, ON M4K 3H9, Canada",
    "formatted_phone_number": "(416) 393-9470",
    "geometry": {
        "location": {
            "lat": 43.67019949999999,
            "lng": -79.34230459999999
        },
        "viewport": {
            "northeast": {
                "lat": 43.67147428029149,
                "lng": -79.34092436970847
            },
            "southwest": {
                "lat": 43.66877631970849,
                "lng": -79.3436223302915
            }
        }
    },
    "icon": "https://maps.gstatic.com/mapfiles/place_api/icons/school-71.png",
    "id": "1f82c220d4ac2ca268ca4c24e9209ee8a9e92f2b",
    "international_phone_number": "+1 416-393-9470",
    "name": "Pape Avenue Junior Public School",
    "place_id": "ChIJwz2xPXzL1IkRmLS3K3Uqh_o",
    "rating": 5,
    "reference": "CmRSAAAAHXWFPpAXe2dosXIWFaE7YOkr27gnQXP2_NnMfbN6MhuvzkIsZoJ1VVKhWJl21AU5EzWpa6jXwtqPLoEhxHuecvZSUO1kOATmfQqvtQtEzEPXfOcjwNs4_5q9eIa77yuTEhC1ayAJjM29v7fjMlI14KKkGhS7ZWpVZM4fFJeyGSkPlEhLp3Sciw",
    "reviews": [
        {
            "author_name": "Randy Randrianarison",
            "author_url": "https://www.google.com/maps/contrib/102965067921675932068/reviews",
            "language": "en",
            "profile_photo_url": "https://lh5.googleusercontent.com/-lsaGj_X4mVQ/AAAAAAAAAAI/AAAAAAAABdM/OVv1b5tWfpg/s128-c0x00000000-cc-rp-mo/photo.jpg",
            "rating": 5,
            "relative_time_description": "2 years ago",
            "text": "Its amazing",
            "time": 1438657101
        },
        {
            "author_name": "Lisa Zhou",
            "author_url": "https://www.google.com/maps/contrib/102034600345925764758/reviews",
            "profile_photo_url": "https://lh3.googleusercontent.com/-8DUc5FKEMHk/AAAAAAAAAAI/AAAAAAAAAHA/s6UUmmGbm2U/s128-c0x00000000-cc-rp-mo-ba4/photo.jpg",
            "rating": 5,
            "relative_time_description": "a year ago",
            "text": "",
            "time": 1496291121
        },
        {
            "author_name": "Jeff Kramp",
            "author_url": "https://www.google.com/maps/contrib/114717863921878220042/reviews",
            "profile_photo_url": "https://lh6.googleusercontent.com/-TSAQsjXAvos/AAAAAAAAAAI/AAAAAAAAKBU/FObjVfQd-F8/s128-c0x00000000-cc-rp-mo/photo.jpg",
            "rating": 5,
            "relative_time_description": "3 years ago",
            "text": "",
            "time": 1410374472
        }
    ],
    "scope": "GOOGLE",
    "types": [
        "school",
        "point_of_interest",
        "establishment"
    ],
    "url": "https://maps.google.com/?cid=18052444314070922392",
    "utc_offset": -240,
    "vicinity": "220 Langley Avenue, Toronto",
    "website": "http://schools.tdsb.on.ca/papeavenue"
}